tdsc_abus2023_pytorch/__init__.py
tdsc_abus2023_pytorch/enums.py
tdsc_abus2023_pytorch/tdsc.py
tdsc_abus2023_pytorch/tdsc_tumors.py
tdsc_abus2023_pytorch/view_transforms.py
tdsc_abus2023_pytorch/utils/__init__.py
tdsc_abus2023_pytorch/utils/downloader.py
tdsc_abus2023_pytorch-0.1.10.dist-info/METADATA
tdsc_abus2023_pytorch-0.1.10.dist-info/WHEEL
tdsc_abus2023_pytorch-0.1.10.dist-info/top_level.txt
tdsc_abus2023_pytorch-0.1.10.dist-info/RECORD
