Metadata-Version: 2.4
Name: tdsc-abus2023-pytorch
Version: 0.1.10
Summary: PyTorch dataset for TDSC ABUS 2023
Home-page: https://github.com/mralinp/tdsc-abus2023-pytorch
Author: Ali Naderi Parizi
Author-email: me@alinaderiparizi.com
Classifier: Programming Language :: Python :: 3
Classifier: License :: OSI Approved :: MIT License
Classifier: Operating System :: OS Independent
Requires-Python: >=3.7
Requires-Dist: torch
Requires-Dist: numpy
Requires-Dist: pandas
Requires-Dist: pynrrd
Requires-Dist: gdown
Dynamic: author
Dynamic: author-email
Dynamic: classifier
Dynamic: description
Dynamic: description-content-type
Dynamic: home-page
Dynamic: requires-dist
Dynamic: requires-python
Dynamic: summary
